library_for_plots/GraphGrid.py
library_for_plots/__init__.py
library_for_plots/example_metal_diffusion.py
library_for_plots/get_subplot_label.py
library_for_plots/myimports.py
library_for_plots/plot_from_file.py
library_for_plots/plot_graph.py
library_for_plots/plot_several_graphs.py
plotlib/GraphGrid.py
plotlib/__init__.py
plotlib/example_metal_diffusion.py
plotlib/get_subplot_label.py
plotlib/myimports.py
plotlib/plot_from_file.py
plotlib/plot_graph.py
plotlib/plot_several_graphs.py
library_for_plots-0.0.1.dist-info/LICENSE
library_for_plots-0.0.1.dist-info/METADATA
library_for_plots-0.0.1.dist-info/WHEEL
library_for_plots-0.0.1.dist-info/top_level.txt
library_for_plots-0.0.1.dist-info/RECORD
