Metadata-Version: 2.1
Name: library_for_plots
Version: 0.0.1
Summary: This is matplotlib wrapper.
Home-page: https://codeberg.org/gorz/plotlib.git
Author: gorz
Author-email: example@gmail.com
Project-URL: Codeberg, https://codeberg.org/gorz
Keywords: plot graphs
Classifier: Programming Language :: Python :: 3.13
Classifier: License :: OSI Approved :: MIT License
Classifier: Operating System :: OS Independent
Requires-Python: >=3.13
License-File: LICENSE
Requires-Dist: matplotlib>=3.10
Requires-Dist: numpy>=2.2.3
